gym_minesweeper/__init__.py
gym_minesweeper/envs/__init__.py
gym_minesweeper/envs/minesweeper.py
gym_minesweeper-0.0.1.dist-info/LICENSE
gym_minesweeper-0.0.1.dist-info/METADATA
gym_minesweeper-0.0.1.dist-info/WHEEL
gym_minesweeper-0.0.1.dist-info/top_level.txt
gym_minesweeper-0.0.1.dist-info/RECORD
