Metadata-Version: 2.1
Name: gym-minesweeper
Version: 0.0.1
Summary: Environment for OpenAI Gym simulating a minesweeper game
Author-email: Zhixing Jeffrey Yao <jeffreyyao@outlook.com>
License: MIT License        
Project-URL: Homepage, https://github.com/Jeffreyyao/gym-minesweeper
Project-URL: Bug Tracker, https://github.com/Jeffreyyao/gym-minesweeper/issues
Classifier: Programming Language :: Python :: 3
Classifier: License :: OSI Approved :: MIT License
Classifier: Operating System :: OS Independent
Requires-Python: >=3.7
License-File: LICENSE
Requires-Dist: gym (>=0.24.1)
Requires-Dist: pygame (>=2.1.2)
